{
  "project_info": {
    "project_number": "24115778083",
    "firebase_url": "https://confetibot-f9e19.firebaseio.com",
    "project_id": "confetibot-f9e19",
    "storage_bucket": "confetibot-f9e19.appspot.com"
  },
  "client": [
    {
      "client_info": {
        "mobilesdk_app_id": "1:24115778083:android:3e4609036524f5ef",
        "android_client_info": {
          "package_name": "com.ayudin.confetti"
        }
      },
      "oauth_client": [
        {
          "client_id": "24115778083-lldj9qnr1bi947qi0ptkccruralmj83g.apps.googleusercontent.com",
          "client_type": 1,
          "android_info": {
            "package_name": "com.ayudin.confetti",
            "certificate_hash": "177e3ec1a7733095fe4da797addd459c926f6925"
          }
        },
        {
          "client_id": "24115778083-v659s566iudi6e7easdfnjme6t9l0bad.apps.googleusercontent.com",
          "client_type": 1,
          "android_info": {
            "package_name": "com.ayudin.confetti",
            "certificate_hash": "ddb14eaec47085d763a51b988440704774677f3f"
          }
        },
        {
          "client_id": "24115778083-4ib15rm22caahqq3k6mk7uh0og7s7pml.apps.googleusercontent.com",
          "client_type": 3
        }
      ],
      "api_key": [
        {
          "current_key": "AIzaSyCRTaDHiUzG2HjcvepcG_I5nD0IJV1bQjE"
        }
      ],
      "services": {
        "appinvite_service": {
          "other_platform_oauth_client": [
            {
              "client_id": "24115778083-4ib15rm22caahqq3k6mk7uh0og7s7pml.apps.googleusercontent.com",
              "client_type": 3
            }
          ]
        }
      },
      "admob_app_id": "ca-app-pub-5846226462716541~1162981272"
    }
  ],
  "configuration_version": "1"
}